{
  "$schema": "http://json-schema.org/draft-04/schema#",
  "key": "breadcrumb",
  "title": "Breadcrumb",
  "description": "Breadcrumb component.",
  "type": "object",
  "properties": {
    "list": {
      "title": "Link List",
      "type": "array",
      "items": {
        "title": "Item",
        "type": "object",
        "properties": {
          "text": {
            "title": "Text",
            "type": "string",
            "format": "text"
          },
          "href": {
            "title": "Link URL",
            "type": "string",
            "format": "text"
          },
          "tracking": {
            "title": "Tracking Label",
            "type": "string",
            "format": "text"
          }
        }
      }
    }
  }
}
